hidabc/pyusb.py
hidabc/hidraw.py
hidabc/__init__.py
hidabc-0.3.0.dist-info/METADATA
hidabc-0.3.0.dist-info/WHEEL
hidabc-0.3.0.dist-info/RECORD
